setup.py
cfnplan/__init__.py
cfnplan/template.py
cfnplan.egg-info/PKG-INFO
cfnplan.egg-info/SOURCES.txt
cfnplan.egg-info/dependency_links.txt
cfnplan.egg-info/top_level.txt
scripts/cfnplan