Metadata-Version: 1.1
Name: cfnplan
Version: 1.0.1
Summary: Simple tool to help you plan for AWS CloudFormation stack updates
Home-page: https://github.com/zsims/cfnplan
Author: Zachary Sims
Author-email: zsims@users.noreply.github.com
License: LICENSE.txt
Keywords: development aws cloudformation cloud
Platform: UNKNOWN
Classifier: Development Status :: 4 - Beta
Classifier: Intended Audience :: Developers
Classifier: Programming Language :: Python :: 3
Classifier: Programming Language :: Python :: 3.2
Classifier: Programming Language :: Python :: 3.3
Classifier: Programming Language :: Python :: 3.4
Classifier: Programming Language :: Python :: 2
Classifier: Programming Language :: Python :: 2.7
